nssql/__init__.py
nssql-3.8.5.dist-info/LICENSE
nssql-3.8.5.dist-info/METADATA
nssql-3.8.5.dist-info/WHEEL
nssql-3.8.5.dist-info/top_level.txt
nssql-3.8.5.dist-info/RECORD
